readyapi_cli/__init__.py
readyapi_cli/__main__.py
readyapi_cli/cli.py
readyapi_cli/discover.py
readyapi_cli/exceptions.py
readyapi_cli/logging.py
readyapi_cli/py.typed
readyapi_cli_slim-0.0.6.dist-info/METADATA
readyapi_cli_slim-0.0.6.dist-info/WHEEL
readyapi_cli_slim-0.0.6.dist-info/entry_points.txt
readyapi_cli_slim-0.0.6.dist-info/licenses/LICENSE
readyapi_cli_slim-0.0.6.dist-info/RECORD
