Metadata-Version: 2.1
Name: readyapi-cli-slim
Version: 0.0.6
Summary: Run and manage ReadyAPI apps from the command line with ReadyAPI CLI. 🚀
Home-page: https://github.com/readyapi/readyapi-cli
Author-Email: KhulnaSoft DevOps <info@khulnasoft.com>
License: MIT
Classifier: Intended Audience :: Information Technology
Classifier: Intended Audience :: System Administrators
Classifier: Operating System :: OS Independent
Classifier: Programming Language :: Python :: 3
Classifier: Programming Language :: Python
Classifier: Topic :: Software Development :: Libraries :: Application Frameworks
Classifier: Topic :: Software Development :: Libraries :: Python Modules
Classifier: Topic :: Software Development :: Libraries
Classifier: Topic :: Software Development
Classifier: Typing :: Typed
Classifier: Development Status :: 4 - Beta
Classifier: Intended Audience :: Developers
Classifier: License :: OSI Approved :: MIT License
Classifier: Programming Language :: Python :: 3 :: Only
Classifier: Programming Language :: Python :: 3.8
Classifier: Programming Language :: Python :: 3.9
Classifier: Programming Language :: Python :: 3.10
Classifier: Programming Language :: Python :: 3.11
Classifier: Programming Language :: Python :: 3.12
Classifier: License :: OSI Approved :: MIT License
Project-URL: Documentation, https://readyapi.khulnasoft.com
Project-URL: Homepage, https://github.com/readyapi/readyapi-cli
Project-URL: Repository, https://github.com/readyapi/readyapi-cli
Requires-Python: >=3.8
Requires-Dist: cligenius>=0.12.3
Requires-Dist: uvicorn[standard]>=0.15.0
Requires-Dist: uvicorn[standard]>=0.15.0; extra == "standard"
Provides-Extra: standard
